{
  "fixed": [
    {
      "fixed": true,
      "key": "manaCost",
      "name": "Open into Wonder",
      "value": "{X}{U}{U}"
    },
    {
      "fixed": true,
      "key": "manaCost",
      "name": "Evolving Wilds",
      "value": ""
    },
    {
      "fixed": true,
      "key": "manaCost",
      "name": "Painted Bluffs",
      "value": ""
    },
    {
      "fixed": true,
      "key": "manaCost",
      "name": "Cascading Cataracts",
      "value": ""
    },
    {
      "fixed": true,
      "key": "manaCost",
      "name": "Cradle of the Accursed",
      "value": ""
    },
    {
      "fixed": true,
      "key": "manaCost",
      "name": "Grasping Dunes",
      "value": ""
    },
    {
      "fixed": true,
      "key": "manaCost",
      "name": "By Force",
      "value": "{X}{R}"
    },
    {
      "fixed": true,
      "key": "types",
      "name": "Nissa, Steward of Elements"
    },
    {
      "fixed": true,
      "key": "manaCost",
      "name": "Nissa, Steward of Elements",
      "value": "{X}{U}{G}"
    },
    {
      "fixed": true,
      "key": "manaCost",
      "name": "Sunscorched Desert",
      "value": ""
    },
    {
      "fixed": true,
      "key": "manaCost",
      "name": "Heaven // Earth",
      "value": ""
    },
    {
      "fixed": true,
      "key": "manaCost",
      "name": "Pull from Tomorrow",
      "value": ""
    },
    {
      "fixed": true,
      "key": "types",
      "name": "Liliana, Death's Majesty"
    },
    {
      "fixed": true,
      "key": "types",
      "name": "Gideon, Martial Pargon"
    },
    {
      "fixed": true,
      "key": "manaCost",
      "name": "Foul Orchard",
      "value": ""
    },
    {
      "fixed": true,
      "key": "manaCost",
      "name": "Stone Quarry",
      "value": ""
    },
    {
      "fixed": true,
      "key": "types",
      "name": "Gideon of the Trials"
    },
    {
      "fixed": true,
      "key": "types",
      "name": "Liliana, Death Wielder"
    },
    {
      "fixed": true,
      "key": "manaCost",
      "name": "Sheltered Thicket",
      "value": ""
    },
    {
      "fixed": true,
      "key": "manaCost",
      "name": "Canyon Slough",
      "value": ""
    },
    {
      "fixed": true,
      "key": "manaCost",
      "name": "Fetid Pools",
      "value": ""
    },
    {
      "fixed": true,
      "key": "manaCost",
      "name": "Scattered Groves",
      "value": ""
    },
    {
      "fixed": true,
      "key": "manaCost",
      "name": "Irrigated Farmland",
      "value": ""
    },
    {
      "fixed": true,
      "key": "manaCost",
      "name": "Forest",
      "value": ""
    },
    {
      "fixed": true,
      "key": "manaCost",
      "name": "Mountain",
      "value": ""
    },
    {
      "fixed": true,
      "key": "manaCost",
      "name": "Swamp",
      "value": ""
    },
    {
      "fixed": true,
      "key": "manaCost",
      "name": "Island",
      "value": ""
    },
    {
      "fixed": true,
      "key": "manaCost",
      "name": "Plains",
      "value": ""
    },
    {
      "fixed": true,
      "key": "manaCost",
      "name": "Pact of Negation",
      "value": "{0}"
    }
  ],
  "unfixed": [
    {
      "key": "url",
      "name": "Commit // Memory",
      "value": ""
    },
    {
      "key": "url",
      "name": "Spring // Mind",
      "value": ""
    },
    {
      "key": "url",
      "name": "Start // Finish",
      "value": ""
    },
    {
      "key": "colors",
      "name": "Heaven // Earth",
      "value": ""
    },
    {
      "key": "url",
      "name": "Heaven // Earth",
      "value": ""
    },
    {
      "key": "url",
      "name": "Reduce // Rubble",
      "value": ""
    },
    {
      "key": "url",
      "name": "Never // Return",
      "value": ""
    },
    {
      "key": "url",
      "name": "Failure // Comply",
      "value": ""
    },
    {
      "key": "loyalty",
      "name": "Liliana, Death's Majesty",
      "value": ""
    },
    {
      "key": "loyalty",
      "name": "Gideon, Martial Pargon",
      "value": ""
    },
    {
      "key": "url",
      "name": "Gideon, Martial Pargon",
      "value": ""
    },
    {
      "key": "url",
      "name": "Dessicated Naga",
      "value": ""
    },
    {
      "key": "url",
      "name": "Foul Orchard",
      "value": ""
    },
    {
      "key": "url",
      "name": "Gideon's Resolve",
      "value": ""
    },
    {
      "key": "url",
      "name": "Liliana's Influence",
      "value": ""
    },
    {
      "key": "url",
      "name": "Companion of the Trials",
      "value": ""
    },
    {
      "key": "url",
      "name": "Stone Quarry",
      "value": ""
    },
    {
      "key": "url",
      "name": "Mouth // Feed",
      "value": ""
    },
    {
      "key": "url",
      "name": "Rags // Riches",
      "value": ""
    },
    {
      "key": "url",
      "name": "Insult // Injury",
      "value": ""
    },
    {
      "key": "url",
      "name": "Cut // Ribbons",
      "value": ""
    },
    {
      "key": "loyalty",
      "name": "Gideon of the Trials",
      "value": ""
    },
    {
      "key": "power",
      "name": "Watchers of the Dead",
      "value": ""
    },
    {
      "key": "toughness",
      "name": "Watchers of the Dead",
      "value": ""
    },
    {
      "key": "url",
      "name": "Onward // Victory",
      "value": ""
    },
    {
      "key": "url",
      "name": "Prepare // Fight",
      "value": ""
    },
    {
      "key": "loyalty",
      "name": "Liliana, Death Wielder",
      "value": ""
    },
    {
      "key": "url",
      "name": "Liliana, Death Wielder",
      "value": ""
    },
    {
      "key": "url",
      "name": "Destined // Lead",
      "value": ""
    },
    {
      "key": "url",
      "name": "Annointer Priest",
      "value": ""
    },
    {
      "key": "url",
      "name": "Tattered Mummy",
      "value": ""
    },
    {
      "key": "url",
      "name": "Graceful Cat",
      "value": ""
    },
    {
      "key": "url",
      "name": "Dusk // Dawn",
      "value": ""
    },
    {
      "key": "number",
      "name": "Dark Ritual",
      "value": ""
    },
    {
      "key": "number",
      "name": "Mind Twist",
      "value": ""
    }
  ]
}